{
  "name": "ibs02pir2",
  "description": "Ingics IBS02PIR2 Device Profile",
  "image": null,
  "type": "DEFAULT",
  "transportType": "DEFAULT",
  "provisionType": "DISABLED",
  "defaultRuleChainId": null,
  "defaultDashboardId": null,
  "defaultQueueName": null,
  "profileData": {
    "configuration": {
      "type": "DEFAULT"
    },
    "transportConfiguration": {
      "type": "DEFAULT"
    },
    "provisionConfiguration": {
      "type": "DISABLED",
      "provisionDeviceSecret": null
    },
    "alarms": null
  },
  "provisionDeviceKey": null,
  "firmwareId": null,
  "softwareId": null,
  "externalId": null,
  "default": false
}